[
    {
        "name": "report_attend_employees_informations",
        "En": "Report Invoices Employees Informations",
        "Ar": "بيانات حضور و غياب الموظفين"
    },
    {
        "name": "report_attend_employees",
        "En": "Attend & Absence Employees",
        "Ar": "حضور و غياب الموظفين"
    },
    {
        "name": "report_attend_employees_menus",
        "En": "Report Invoices Menu",
        "Ar": "قائمة تقرير فاتورة"
    },
    {
        "name": "view_employees_attend",
        "En": "View Employees Attend",
        "Ar": "عرض حضور الموظفين"
    },
    {
        "name": "report_attend_details",
        "En": "Employees Attend Details",
        "Ar": "تفاصيل حضور الموظفين"
    },
    {
        "name": "attend_count",
        "En": "Attend Count",
        "Ar": "عدد مرات الحضور"
    },
    {
        "name": "absence_count",
        "En": "Absence Count",
        "Ar": "عدد مرات الغياب"
    }
]