[{
        "name": "scan_centers",
        "en": "Scan Labs",
        "ar": "معامل الاشعة"
    },
    {
        "name": "scan_centers_new",
        "en": "New Scan Lab",
        "ar": "معمل اشعة  جديد"
    },

    {
        "name": "scan_centers_add",
        "en": "Add Scan Lab",
        "ar": "اضافة معمل اشعة "
    },
    {
        "name": "scan_centers_edit",
        "en": "Edit Scan Lab",
        "ar": "تعديل معمل اشعة "
    },
    {
        "name": "scan_centers_details",
        "en": "Scan Lab Details",
        "ar": "تفاصيل المعمل اشعة "
    },
    {
        "name": "scan_centers_delete",
        "en": "Delete Scan Lab",
        "ar": "حذف معمل اشعة "
    },
    {
        "name": "scan_centers_name",
        "en": "Scan Lab Name",
        "ar": "إسم المعمل اشعة "
    }
    ,
    {
        "name": "scan_names",
        "en": "Scan Names",
        "ar": "إسماء الاشعات"
    }

    

]