[
    {
        "name": "doctors_visits",
        "En": "Examination books",
        "Ar": "حجز كشف"
    },
    {
        "name": "doctor_visit",
        "En": "Examination book",
        "Ar": "حجز كشف"
    },
    {
        "name": "must_pay_full_price_examination",
        "En": "Must Pay the full price of the Examination",
        "Ar": "يجب دفع سعر الحجز كاملا"
    },
    {
        "name": "place_examination",
        "En": "Place examination",
        "Ar": "مكان الحجز"
    },
    {
        "name": "doctors_visits_new",
        "En": "New Examination book",
        "Ar": "حجز كشف جديدة"
    },
    {
        "name": "doctor_visit_price",
        "En": "Visit Price",
        "Ar": "سعر الحجز"
    },
    {
        "name": "doctor_notes",
        "En": "Doctor Notes",
        "Ar": "ملاحظات الطبيب"
    },
    {
        "name": "visit_type",
        "En": "Visit Type",
        "Ar": "نوع الحجز"
    },
    {
        "name": "doctor_visit_type",
        "En": "Examination book Type",
        "Ar": "نوع حجز الكشف"
    },
    {
        "name": "cannot_booked_holiday_clinic",
        "En": "Can not be booked on holiday for the clinic",
        "Ar": "لا يمكن الحجز اليوم عطلة للعيادة"
    },
    {
        "name": "view_appointments",
        "En": "View appointments",
        "Ar": "عرض المواعيد"
    },
    {
        "name": "doctors_visits_book",
        "En": "Doctors Examination booking",
        "Ar": " حجز كشف طبيب"
    },
    {
        "name": "dont_book",
        "En": "Do Not Booking",
        "Ar": "لم يتم الحجز"
    },
    {
        "name": "patient",
        "En": "Patient Name",
        "Ar": " إسم المريض"
    },
    {
        "name": "patient_search",
        "En": "Patients Search",
        "Ar": "بحث المرضى"
    },
    {
        "name": "address_search",
        "En": "Address Search",
        "Ar": "بحث العنوان"
    },
    {
        "name": "hospital_search",
        "En": "Hospital Search",
        "Ar": "بحث المستشفى"
    },
    {
        "name": "doctor_search",
        "En": "Doctor Search",
        "Ar": "بحث الطبيب"
    },
    {
        "name": "spicialty_search",
        "En": "Spicialty Search",
        "Ar": "بحث التخصص"
    },
    {
        "name": "clinic_search",
        "En": "Clinic Search",
        "Ar": "بحث العيادة"
    },
    {
        "name": "doctors_visits_add",
        "En": "Add Examination book",
        "Ar": "إضافة حجز كشف"
    },
    {
        "name": "doctors_visits_edit",
        "En": "Edit Examination book",
        "Ar": "تعديل حجز كشف"
    },
    {
        "name": "doctors_visits_details",
        "En": "Examination Book Details",
        "Ar": "تفاصيل الحجز"
    },
    {
        "name": "doctors_visits_delete",
        "En": "Delete Examination book",
        "Ar": "حذف حجز كشف"
    },
    {
        "name": "doctors_visits_select",
        "En": "Select",
        "Ar": "تحديد"
    },
    {
        "name": "view_doctors",
        "En": "View Doctors",
        "Ar": "عرض الأطباء"
    },
    {
        "name": "booking_date",
        "En": "Booking Date",
        "Ar": "تاريخ الحجز"
    },
    {
        "name": "visit_date",
        "En": "Examination Date",
        "Ar": "تاريخ الحجز"
    },
    {
        "name": "visit_number",
        "En": "Visit Number",
        "Ar": "رقم الحجز"
    },
    {
        "name": "visit_code",
        "En": "Visit Code",
        "Ar": "كود الحجز"
    },
    {
        "name": "shift_name",
        "En": "Shift Name",
        "Ar": "إسم الشيفت "
    },
    {
        "name": "clinics",
        "En": "Clinics",
        "Ar": "العيادات"
    },
    {
        "name": "searching",
        "En": "Searching",
        "Ar": "البحـــــــــــث"
    },
    {
        "name": "work_times",
        "En": "Work Times",
        "Ar": "مواعيد العمل"
    },
    {
        "name": "work_day",
        "En": "Day ",
        "Ar": "اليوم"
    },
    {
        "name": "work_from",
        "En": "From ",
        "Ar": "من"
    },
    {
        "name": "work_to",
        "En": "Work To",
        "Ar": "إلى"
    },
    {
        "name": "doctor_name",
        "En": "Doctor Name",
        "Ar": "إسم الطبيب"
    },
    {
        "name": "doctor",
        "En": "Doctor",
        "Ar": "الطبيب"
    },
    {
        "name": "medicine_name",
        "En": "Medicine name",
        "Ar": "إسم الدواء"
    },
    {
        "name": "doctors_visits_name",
        "En": "Examination Name",
        "Ar": "إسم الحجز"
    },
    {
        "name": "scan",
        "En": "Scans",
        "Ar": "الأشعة"
    },
    {
        "name": "analysis",
        "En": "Analysis",
        "Ar": "التحاليل"
    },
    {
        "name": "prescription_treatment",
        "En": "Prescription treatment",
        "Ar": "الروشتة العلاجية"
    },
    {
        "name": "transferred_department",
        "En": "Transferred Department",
        "Ar": "القسم المحول له"
    },
    {
        "name": "next_counseling_date",
        "En": "Next Counseling Date",
        "Ar": "تاريخ الإستشارة القادم"
    },
    {
        "name": "next_counseling_re_detection",
        "En": "Next re-detection Date",
        "Ar": "تاريخ إعادة الكشف القادم"
    },
    {
        "name": "must_selected_time",
        "En": "Must Selected Time",
        "Ar": "يجب إختيار ميعاد"
    },
    {
        "name": "result_visit",
        "En": "The result of the Examination",
        "Ar": "نتيجة الكشف"
    },
    {
        "name": "diagnosis",
        "En": "Diagnosis",
        "Ar": "التشخيص"
    },
    {
        "name": "special_notes",
        "En": "Special Notes",
        "Ar": "ملاحظات خاصة"
    },
    {
        "name": "diagnosis_after_visit",
        "En": "Diagnosis After Examination",
        "Ar": "التشخيص بعد الكشف"
    },
    {
        "name": "status",
        "En": "Status",
        "Ar": "الحالة"
    },
    {
        "name": "booking",
        "En": "Booking",
        "Ar": "حجز"
    },
    {
        "name": "notes_before",
        "En": "Notes Before Detection",
        "Ar": "ملاحظات قبل الكشف"
    },
    {
        "name": "confirm_delete",
        "En": "Confirm Book Delete !",
        "Ar": "تأكيد حذف الحجز !"
    },
    {
        "name": "on_hold",
        "En": "On hold",
        "Ar": "قيد الإنتظار"
    },
    {
        "name": "just_booking",
        "En": "Just Booking",
        "Ar": "حجز فقط"
    },
    {
        "name": "waiting_in_clinic",
        "En": "Waiting in the clinic",
        "Ar": "إنتظار في العيادة"
    },
    {
        "name": "at_the_doctor",
        "En": "At The Doctor",
        "Ar": "عند الطبيب"
    },
    {
        "name": "done_detection",
        "En": "Done Detection",
        "Ar": "تم الكشف"
    },
    {
        "name": "blood_pressure",
        "En": "Blood Pressure",
        "Ar": "ضغط الدم"
    },
    {
        "name": "breathing",
        "En": "Breathing",
        "Ar": "التنفس"
    },
    {
        "name": "heart_beats",
        "En": "Heart Beats",
        "Ar": "نبضات القلب"
    },
    {
        "name": "body_temperature",
        "En": "Body temperature",
        "Ar": "حرارة الجسم"
    },
    {
        "name": "Sugar",
        "En": "Sugar",
        "Ar": "السكر"
    },
    {
        "name": "previous_operations",
        "En": "Previous operations",
        "Ar": "عمليات سابقة"
    },
    {
        "name": "patient_advice",
        "En": "Patient Advice",
        "Ar": "نصائح للمريض"
    },
    {
        "name": "examination_before_detection",
        "En": "Examination before detection",
        "Ar": "فحص قبل الكشف"
    },
    {
        "name": "done_attendance",
        "En": "Attendance",
        "Ar": "تم الحضور"
    },
    {
        "name": "done_access_doctor",
        "En": "Access to the doctor",
        "Ar": "دخول للطبيب"
    },
    {
        "name": "done_detected",
        "En": "Detected",
        "Ar": "تم الكشف"
    },
    {
        "name": "medicine_unit",
        "En": "Medicine Unit",
        "Ar": "وحدة الدواء"
    },
    {
        "name": "medicine_search",
        "En": "Medicines Search",
        "Ar": "بحث الأدوية"
    },
    {
        "name": "alternative_medicines",
        "En": "Alternative Medicines",
        "Ar": "أدوية بديلة"
    },
    {
        "name": "favorite_foods_drinks",
        "En": "Favorite foods and drinks",
        "Ar": "الأطعمة و المشروبات المفضلة"
    },
    {
        "name": "forbidden_foods_drinks",
        "En": "Forbidden foods and drinks",
        "Ar": "الأطعمة و المشروبات الممنوعة"
    }
]